breeze_rect/__init__.py
breeze_rect-0.1.1.dist-info/LICENSE
breeze_rect-0.1.1.dist-info/METADATA
breeze_rect-0.1.1.dist-info/WHEEL
breeze_rect-0.1.1.dist-info/top_level.txt
breeze_rect-0.1.1.dist-info/RECORD
